gander/__init__.py
gander/helper_indicators.py
gander/indicators.py
gander/plotting.py
gander/tests/__init__.py
gander/tests/data_for_tests.py
gander/tests/test_indicators.py
gander-0.0.4.dist-info/COPYING
gander-0.0.4.dist-info/METADATA
gander-0.0.4.dist-info/WHEEL
gander-0.0.4.dist-info/top_level.txt
gander-0.0.4.dist-info/RECORD
