Metadata-Version: 2.1
Name: gander
Version: 0.0.4
Summary: Technical indicators for the stock market
Home-page: http://github.com/ekkobit/gander
Author: Ole Olaussen, Xuan Ling
Author-email: ole.olaussen@ekkobit.com, xuan.ling@ekkobit.com
License: MIT
Platform: UNKNOWN
Classifier: Development Status :: 3 - Alpha
Classifier: License :: OSI Approved :: GNU General Public License v3 or later (GPLv3+)
Classifier: Programming Language :: Python :: 3
Classifier: Topic :: Office/Business :: Financial :: Investment
Requires-Dist: pandas
Requires-Dist: numpy
Requires-Dist: matplotlib
